wagtailnhsstyle/__init__.py
wagtailnhsstyle/blocks.py
wagtailnhsstyle/migrations/__init__.py
wagtailnhsstyle/settings/__init__.py
wagtailnhsstyle/settings/apps.py
wagtailnhsstyle/settings/models.py
wagtailnhsstyle/settings/migrations/0001_initial.py
wagtailnhsstyle/settings/migrations/__init__.py
wagtailnhsstyle/static/.DS_Store
wagtailnhsstyle/static/wagtailnhsstyle/css/fixes.css
wagtailnhsstyle/static/wagtailnhsstyle/css/nhsuk-0.8.0.min.css
wagtailnhsstyle/static/wagtailnhsstyle/css/wagtail-nhs.min.css
wagtailnhsstyle/static/wagtailnhsstyle/js/nhsuk-0.8.0.min.js
wagtailnhsstyle/templates/wagtailnhsstyle/action_link.html
wagtailnhsstyle/templates/wagtailnhsstyle/breadcrumb.html
wagtailnhsstyle/templates/wagtailnhsstyle/breadcrumb_back.html
wagtailnhsstyle/templates/wagtailnhsstyle/breadcrumb_item.html
wagtailnhsstyle/templates/wagtailnhsstyle/care_card.html
wagtailnhsstyle/templates/wagtailnhsstyle/header.html
wagtailnhsstyle/templates/wagtailnhsstyle/warning_callout.html
wagtailnhsstyle/templates/wagtailnhsstyle/header/logo.html
wagtailnhsstyle/templates/wagtailnhsstyle/header/menu.html
wagtailnhsstyle/templates/wagtailnhsstyle/header/menu_link.html
wagtailnhsstyle/templates/wagtailnhsstyle/header/menu_toggle.html
wagtailnhsstyle/templates/wagtailnhsstyle/header/search.html
wagtailnhsstyle/templatetags/__init__.py
wagtailnhsstyle/templatetags/nhsstyle_tags.py
wagtail_nhs_style-0.1.0.dist-info/METADATA
wagtail_nhs_style-0.1.0.dist-info/WHEEL
wagtail_nhs_style-0.1.0.dist-info/top_level.txt
wagtail_nhs_style-0.1.0.dist-info/RECORD
