Metadata-Version: 2.1
Name: wagtail-nhs-style
Version: 0.1.0
Summary: NHS Frontend Styles for Wagtail
Home-page: https://github.com/nhsuk/wagtail-nhs-style
Author: Mike Monteith
Author-email: <mike.monteith@nhs.net>
License: UNKNOWN
Platform: UNKNOWN
Requires-Dist: Wagtail (>=2.0)
Provides-Extra: testing
